Metadata-Version: 2.1
Name: odoo-addon-account_general_ledger_contra_accounts
Version: 18.0.1.0.0
Requires-Python: >=3.10
Requires-Dist: odoo-addon-account_move_line_contra_accounts==18.0.*
Requires-Dist: odoo==18.0.*
Summary: Add contra accounts to general ledger.
Home-page: https://www.mint-system.ch/
License: OPL-1
Author: Mint System GmbH
Classifier: Programming Language :: Python
Classifier: Framework :: Odoo
Classifier: Framework :: Odoo :: 18.0
